custom/__init__.py
custom/app.py
custom/chainmath.py
custom/future.py
custom/optiondata.py
custom/ordermgmt.py
custom/strategy.py
custom/symbolload.py
ibtools/__init__.py
ibtools/optionchain.py
ibtools/optionmarketdata.py
ibtools/tools.py
ibtools-0.7.dist-info/LICENSE
ibtools-0.7.dist-info/METADATA
ibtools-0.7.dist-info/WHEEL
ibtools-0.7.dist-info/top_level.txt
ibtools-0.7.dist-info/RECORD
